pysimpleig/__a1.py
pysimpleig/__init__.py
pysimpleig/conversions.py
pysimpleig/exceptions.py
pysimpleig/library.py
pysimpleig/login.py
pysimpleig/syntaxes.py
pysimpleig-1.0.6.dist-info/METADATA
pysimpleig-1.0.6.dist-info/WHEEL
pysimpleig-1.0.6.dist-info/top_level.txt
pysimpleig-1.0.6.dist-info/RECORD
